libcombine/__init__.py
libcombine/_libcombine.cpython-313-i386-linux-gnu.so
python_libcombine-0.2.20.dist-info/top_level.txt
python_libcombine-0.2.20.dist-info/RECORD
python_libcombine-0.2.20.dist-info/LICENSE.md
python_libcombine-0.2.20.dist-info/METADATA
python_libcombine-0.2.20.dist-info/WHEEL
