Metadata-Version: 2.1
Name: python-libcombine
Version: 0.2.20
Summary: LibCombine Python API
Home-page: https://github.com/sbmlteam/libcombine
Author: Frank T. Bergmann
Author-email: fbergman@caltech.edu
License: BSD
License-File: LICENSE.md
